sqlalchemy_mixins/__init__.py
sqlalchemy_mixins/__init__.pyi
sqlalchemy_mixins/activerecord.py
sqlalchemy_mixins/activerecord.pyi
sqlalchemy_mixins/eagerload.py
sqlalchemy_mixins/eagerload.pyi
sqlalchemy_mixins/inspection.py
sqlalchemy_mixins/inspection.pyi
sqlalchemy_mixins/py.typed
sqlalchemy_mixins/repr.py
sqlalchemy_mixins/repr.pyi
sqlalchemy_mixins/serialize.py
sqlalchemy_mixins/serialize.pyi
sqlalchemy_mixins/session.py
sqlalchemy_mixins/session.pyi
sqlalchemy_mixins/smartquery.py
sqlalchemy_mixins/smartquery.pyi
sqlalchemy_mixins/timestamp.py
sqlalchemy_mixins/utils.py
sqlalchemy_mixins/utils.pyi
sqlalchemy_mixins-2.0.5.dist-info/LICENSE.txt
sqlalchemy_mixins-2.0.5.dist-info/METADATA
sqlalchemy_mixins-2.0.5.dist-info/WHEEL
sqlalchemy_mixins-2.0.5.dist-info/top_level.txt
sqlalchemy_mixins-2.0.5.dist-info/RECORD
